cms_lab_carousel/__init__.py
cms_lab_carousel/admin.py
cms_lab_carousel/cms_plugins.py
cms_lab_carousel/cms_toolbar.py
cms_lab_carousel/models.py
cms_lab_carousel/tests.py
cms_lab_carousel/views.py
cms_lab_carousel/static/cms_lab_carousel/app.css
cms_lab_carousel/static/cms_lab_carousel/orange-pixel.gif
cms_lab_carousel/templates/cms_lab_carousel/_buttons.html
cms_lab_carousel/templates/cms_lab_carousel/_carousel-controls.html
cms_lab_carousel/templates/cms_lab_carousel/_carousel-footer.html
cms_lab_carousel/templates/cms_lab_carousel/_carousel-header.html
cms_lab_carousel/templates/cms_lab_carousel/_carousel-indicators.html
cms_lab_carousel/templates/cms_lab_carousel/_modal.html
cms_lab_carousel/templates/cms_lab_carousel/_slide.html
cms_lab_carousel/templates/cms_lab_carousel/plugin.html
djangocms_lab_carousel-0.2.1.dist-info/DESCRIPTION.rst
djangocms_lab_carousel-0.2.1.dist-info/METADATA
djangocms_lab_carousel-0.2.1.dist-info/RECORD
djangocms_lab_carousel-0.2.1.dist-info/WHEEL
djangocms_lab_carousel-0.2.1.dist-info/metadata.json
djangocms_lab_carousel-0.2.1.dist-info/top_level.txt
